[
  {
    "id": 861,
    "word": "obstacle"
  },
  {
    "id": 862,
    "word": "architecture"
  },
  {
    "id": 863,
    "word": "stem"
  },
  {
    "id": 864,
    "word": "illusion"
  },
  {
    "id": 865,
    "word": "discrimination"
  },
  {
    "id": 866,
    "word": "shame"
  },
  {
    "id": 867,
    "word": "drought"
  },
  {
    "id": 868,
    "word": "flavor"
  },
  {
    "id": 869,
    "word": "portion"
  },
  {
    "id": 870,
    "word": "recipe"
  },
  {
    "id": 871,
    "word": "luxury"
  },
  {
    "id": 872,
    "word": "chip"
  },
  {
    "id": 873,
    "word": "ritual"
  },
  {
    "id": 874,
    "word": "sake"
  },
  {
    "id": 875,
    "word": "prefecture"
  },
  {
    "id": 876,
    "word": "council"
  },
  {
    "id": 877,
    "word": "administration"
  },
  {
    "id": 878,
    "word": "curriculum"
  },
  {
    "id": 879,
    "word": "precious"
  },
  {
    "id": 880,
    "word": "generous"
  }
]